collective.playlist-1.0.0-py3.9-nspkg.pth
collective/playlist/__init__.py
collective/playlist/configure.zcml
collective/playlist/interfaces.py
collective/playlist/permissions.zcml
collective/playlist/setuphandlers.py
collective/playlist/testing.py
collective/playlist/upgrades.py
collective/playlist/upgrades.zcml
collective/playlist/browser/__init__.py
collective/playlist/browser/configure.zcml
collective/playlist/browser/settings.py
collective/playlist/browser/viewlets.py
collective/playlist/browser/views.py
collective/playlist/browser/overrides/.gitkeep
collective/playlist/browser/static/.gitkeep
collective/playlist/browser/static/bundle-collectiveplaylist-compiled.js
collective/playlist/browser/static/bundle-collectiveplaylist.js
collective/playlist/browser/static/collectiveplaylist.css
collective/playlist/browser/static/collectiveplaylist.css.map
collective/playlist/browser/static/collectiveplaylist.js
collective/playlist/browser/static/collectiveplaylist.js.map
collective/playlist/browser/static/pat-collectiveplaylist.js
collective/playlist/browser/static/pat-collectiveplaylist.less
collective/playlist/browser/static/extern/jplayer-flat-audio-theme.css
collective/playlist/browser/static/extern/jplayer.playlist.min.js
collective/playlist/browser/static/extern/jquery.jplayer.js
collective/playlist/browser/static/extern/jquery.jplayer.min.js
collective/playlist/browser/static/extern/jquery.min.js
collective/playlist/browser/static/extern/pjax.min.js
collective/playlist/browser/static/extern/require.js
collective/playlist/browser/static/extern/less/_animated.less
collective/playlist/browser/static/extern/less/_bordered-pulled.less
collective/playlist/browser/static/extern/less/_core.less
collective/playlist/browser/static/extern/less/_fixed-width.less
collective/playlist/browser/static/extern/less/_icons.less
collective/playlist/browser/static/extern/less/_larger.less
collective/playlist/browser/static/extern/less/_list.less
collective.playlist-1.0.0.dist-info/LICENSE.GPL
collective.playlist-1.0.0.dist-info/LICENSE.rst
collective.playlist-1.0.0.dist-info/METADATA
collective.playlist-1.0.0.dist-info/WHEEL
collective.playlist-1.0.0.dist-info/entry_points.txt
collective.playlist-1.0.0.dist-info/namespace_packages.txt
collective.playlist-1.0.0.dist-info/top_level.txt
collective.playlist-1.0.0.dist-info/RECORD
