Metadata-Version: 2.1
Name: collective.playlist
Version: 1.0.0
Summary: Audio playlist player for Plone
Home-page: https://pypi.python.org/pypi/collective.playlist
Author: ksuess
Author-email: k.suess@rohberg.ch
License: GPL version 2
Keywords: audio player playlist Plone
Classifier: Topic :: Multimedia :: Sound/Audio :: Players
Classifier: Development Status :: 5 - Production/Stable
Classifier: Environment :: Web Environment
Classifier: Framework :: Plone :: 5.2
Classifier: Programming Language :: Python :: 3.7
Classifier: Programming Language :: Python :: 3.8
Classifier: Programming Language :: Python :: 3.9
Classifier: Operating System :: OS Independent
Classifier: License :: OSI Approved :: GNU General Public License v2 (GPLv2)
License-File: LICENSE.GPL
License-File: LICENSE.rst
Requires-Dist: plone.app.dexterity
Requires-Dist: plone.api
Requires-Dist: Products.GenericSetup (>=1.8.2)
Requires-Dist: setuptools
Requires-Dist: z3c.jbot
Provides-Extra: test
Requires-Dist: plone.testing (>=5.0.0) ; extra == 'test'
Requires-Dist: plone.app.testing[robot] ; extra == 'test'
Requires-Dist: plone.app.robotframework ; extra == 'test'
